{"pz1+xRE774xzho6sLgOjYw==":"301.jpg","Rw154wr9yGNMaJAKpAL/fQ==":"302.jpg","CvyEfhk4WyPEeGPlrWLlvA==":"303.jpg","Q1bJppN69sfORPHQPOgjhw==":"304.jpg","bQfFnkVhRu/+Y8wY08t3Dw==":"305.jpg","FFc5FLjiJGNItxPEh4jzAw==":"305.jpeg","duRTq5YH9XNUeaWWTWynkA==":"305-1.jpeg","OT1MO/pqkrM5cAjqKFCWcw==":"305-2.jpeg","ySCnmDUQzYRc9J8xciWD/A==":"305-3.jpeg","vkLMsYTmukah/PfB4/3QBg==":"306.jpg","4vHnoBYowURrLkTOswVWPA==":"306.jpeg","XN6xdPrphtlbOgSoNI80ug==":"306-1.jpeg","0s8eHQlqLV8tL9xs20ti7w==":"307.jpg","fJ0QzqfFcXyzjmYoUx11uA==":"308.jpg","u4emsNB4AMyUYEJ1Qez9kw==":"308.jpeg","xM3smV0BOcVBtffc+036Eg==":"309.jpg","RioyTi/K/TFIvm+j/l7DrQ==":"310.jpg","oOVcDWxB/l7Nny3ZIi2ZSg==":"311.jpg","fSAy4Z8A75oAPxgyICiADw==":"pexels-sound-on-3394650.jpg","PJcyM87FH0GojiQ1LX1lVQ==":"311-1.jpg","MN6cifIPx6/B85ca6T21bg==":"314.jpg","SUhRSWoaY7Sshr37X9kV2A==":"ammar-abu-zaid-ap8lq6de8fa-unsplash.jpg","uweaakiMeCz+RDEtpxsZag==":"315.jpg","YCnZrbjLEkgp580tLVuMww==":"309-561x374.jpg","dHrjeNdexbs63K+KJVchmA==":"310-561x701.jpg","gNSTrZstg0PMN8Oo6V4RnQ==":"3011-1200x673.jpg","rllVDUoW/5R8EqVZvA1Iag==":"303-1200x800.jpg","PKFbQm13L7EmQ+cCrT07pw==":"304-1200x800.jpg","YbPR2rv0FZfvW9nmp7U0sw==":"037-1200x800.jpg","Oo+/Ke9PIWXJppWSfoWPJw==":"302-1200x675.jpg","d+GzzZ5F7TuOxJv6LQRabw==":"309-500x333.jpg","hHLVIxxC5Fk8hZWpXFjP8w==":"310-500x625.jpg","vcOQ4sBqYhZRFEgdQHl+ow==":"317-500x625.jpg","88lpO2qrfVCwAEmdX2zdAw==":"313-500x500.jpg","l/8YmOwnX51CFku87WTKdw==":"311-500x331.jpg","UjM/o1TGUSabw1/kK6Wqhw==":"314-500x333.jpg","Nb7bakhzOVGQYd0rGZ0TbQ==":"316-500x350.jpg","f5b+XIF6xfMCsAwEFVxGyQ==":"315-500x333.jpg","0PCJP9I5V3hT3idLgRFI1Q==":"305-1200x805.jpeg","rnN0FCQU/j3IESPSSBeafQ==":"306-1200x1780.jpeg","BVtqi8ch7jSXhs1uPsFb1g==":"306-1-1200x1780.jpeg","9zwzUszBA8NKrmDwcNgtvg==":"307-1200x800.jpg","yW6vF8AZfL4CsurpwXeJ+g==":"308-1200x798.jpg","YD/muPNllywxZqAEr+1EYg==":"electronic-device-1.png","S8TKJLKlbe22y4dikLXJ6g==":"hafsa%20logo%202%20kopyas%C4%B1%2031.svg"}